contextfs/__init__.py
contextfs/autoindex.py
contextfs/backend_factory.py
contextfs/config.py
contextfs/core.py
contextfs/embedding.py
contextfs/fts.py
contextfs/graph_backend.py
contextfs/memory_lineage.py
contextfs/postgres_backend.py
contextfs/rag.py
contextfs/schemas.py
contextfs/storage_protocol.py
contextfs/storage_router.py
contextfs/agents/__init__.py
contextfs/agents/base.py
contextfs/agents/providers.py
contextfs/auth/__init__.py
contextfs/auth/api_keys.py
contextfs/auth/middleware.py
contextfs/auth/storage/__init__.py
contextfs/auth/storage/base.py
contextfs/auth/storage/factory.py
contextfs/auth/storage/postgres.py
contextfs/auth/storage/sqlite.py
contextfs/billing/__init__.py
contextfs/billing/stripe_service.py
contextfs/billing/tiers.py
contextfs/billing/webhooks.py
contextfs/cli/__init__.py
contextfs/cli/__main__.py
contextfs/cli/cloud.py
contextfs/cli/index.py
contextfs/cli/install.py
contextfs/cli/memory.py
contextfs/cli/server.py
contextfs/cli/utils.py
contextfs/cli/services/__init__.py
contextfs/cli/services/chroma.py
contextfs/cli/services/mcp.py
contextfs/cli/services/pid.py
contextfs/encryption/__init__.py
contextfs/encryption/client_crypto.py
contextfs/filetypes/__init__.py
contextfs/filetypes/base.py
contextfs/filetypes/integration.py
contextfs/filetypes/linker.py
contextfs/filetypes/registry.py
contextfs/filetypes/handlers/__init__.py
contextfs/filetypes/handlers/config.py
contextfs/filetypes/handlers/cpp.py
contextfs/filetypes/handlers/csharp.py
contextfs/filetypes/handlers/generic.py
contextfs/filetypes/handlers/go.py
contextfs/filetypes/handlers/java.py
contextfs/filetypes/handlers/javascript.py
contextfs/filetypes/handlers/latex.py
contextfs/filetypes/handlers/markdown.py
contextfs/filetypes/handlers/php.py
contextfs/filetypes/handlers/python.py
contextfs/filetypes/handlers/ruby.py
contextfs/filetypes/handlers/rust.py
contextfs/filetypes/handlers/shell.py
contextfs/filetypes/handlers/sql.py
contextfs/filetypes/handlers/swift.py
contextfs-0.2.35.dist-info/METADATA
contextfs-0.2.35.dist-info/WHEEL
contextfs-0.2.35.dist-info/entry_points.txt
contextfs-0.2.35.dist-info/RECORD
