Metadata-Version: 2.4
Name: contextfs
Version: 0.2.35
Summary: Universal AI memory layer - cross-client, cross-repo context management with RAG
Project-URL: Homepage, https://github.com/MagnetonIO/contextfs
Project-URL: Repository, https://github.com/MagnetonIO/contextfs
Author: The YonedaAI Collaboration
Author-email: Matthew Long <mlong@contextfs.ai>
License: MIT
Keywords: agents,ai,claude,codex,context,gemini,llm,mcp,memory,rag
Classifier: Development Status :: 4 - Beta
Classifier: Intended Audience :: Developers
Classifier: License :: OSI Approved :: MIT License
Classifier: Programming Language :: Python :: 3.10
Classifier: Programming Language :: Python :: 3.11
Classifier: Programming Language :: Python :: 3.12
Classifier: Topic :: Scientific/Engineering :: Artificial Intelligence
Requires-Python: >=3.10
Requires-Dist: aiosqlite>=0.19.0
Requires-Dist: alembic>=1.18.0
Requires-Dist: anthropic>=0.76.0
Requires-Dist: bcrypt>=4.2.0
Requires-Dist: chromadb>=1.4.0
Requires-Dist: cryptography>=46.0.0
Requires-Dist: fastapi>=0.128.0
Requires-Dist: fastembed>=0.4.0
Requires-Dist: gitpython>=3.1.46
Requires-Dist: jsonschema>=4.23.0
Requires-Dist: mcp>=1.25.0
Requires-Dist: openai>=2.15.0
Requires-Dist: pydantic-settings>=2.7.0
Requires-Dist: pydantic>=2.12.0
Requires-Dist: pyjwt>=2.10.0
Requires-Dist: python-dotenv>=1.0.1
Requires-Dist: rich>=14.2.0
Requires-Dist: sse-starlette>=2.0.0
Requires-Dist: tiktoken>=0.8.0
Requires-Dist: typer>=0.21.0
Requires-Dist: uvicorn>=0.40.0
Provides-Extra: all
Requires-Dist: asyncpg>=0.30.0; extra == 'all'
Requires-Dist: fastapi>=0.128.0; extra == 'all'
Requires-Dist: psycopg2-binary>=2.9.10; extra == 'all'
Requires-Dist: stripe>=14.0.0; extra == 'all'
Requires-Dist: uvicorn>=0.40.0; extra == 'all'
Requires-Dist: websockets>=14.0; extra == 'all'
Provides-Extra: cloud
Requires-Dist: stripe>=14.0.0; extra == 'cloud'
Provides-Extra: dev
Requires-Dist: mypy>=1.13.0; extra == 'dev'
Requires-Dist: pre-commit>=4.0.0; extra == 'dev'
Requires-Dist: pytest-asyncio>=0.24.0; extra == 'dev'
Requires-Dist: pytest-cov>=6.0.0; extra == 'dev'
Requires-Dist: pytest>=9.0.0; extra == 'dev'
Requires-Dist: ruff>=0.14.0; extra == 'dev'
Requires-Dist: stripe>=14.0.0; extra == 'dev'
Provides-Extra: docs
Requires-Dist: mkdocs-material>=9.5.0; extra == 'docs'
Requires-Dist: mkdocstrings[python]>=0.27.0; extra == 'docs'
Requires-Dist: pymdown-extensions>=10.12; extra == 'docs'
Provides-Extra: gpu
Requires-Dist: fastembed-gpu>=0.4.0; extra == 'gpu'
Provides-Extra: postgres
Requires-Dist: asyncpg>=0.30.0; extra == 'postgres'
Requires-Dist: psycopg2-binary>=2.9.10; extra == 'postgres'
Provides-Extra: torch
Requires-Dist: sentence-transformers>=5.2.0; extra == 'torch'
Provides-Extra: web
Requires-Dist: fastapi>=0.128.0; extra == 'web'
Requires-Dist: uvicorn>=0.40.0; extra == 'web'
Requires-Dist: websockets>=14.0; extra == 'web'
